trayan/__init__.py
trayan/core/__init__.py
trayan/core/base.py
trayan/core/quick.py
trayan/core/aio/__init__.py
trayan/core/aio/client.py
trayan/core/aio/quick.py
trayan/core/sync/__init__.py
trayan/core/sync/client.py
trayan/core/sync/quick.py
trayan/models/__init__.py
trayan/models/errors/__init__.py
trayan/models/errors/parse.py
trayan/models/errors/request.py
trayan/models/request/__init__.py
trayan/models/request/method.py
trayan/models/translator/__init__.py
trayan/models/translator/api.py
trayan/models/translator/language.py
trayan/utils/__init__.py
trayan/utils/cache.py
tra_yan-0.1.0.dist-info/LICENSE
tra_yan-0.1.0.dist-info/METADATA
tra_yan-0.1.0.dist-info/WHEEL
tra_yan-0.1.0.dist-info/top_level.txt
tra_yan-0.1.0.dist-info/RECORD
