Metadata-Version: 2.1
Name: tra-yan
Version: 0.1.0
Home-page: https://github.com/re1von/tra-yan
Author: re1von project
Author-email: re1von_project@bk.ru
License-File: LICENSE
Requires-Dist: httpx[socks] (>=0.23.3)
Requires-Dist: aiofiles (>=22.0.1)
